<?xml version="1.0" encoding="utf-8" standalone="no" ?>
<map xmlns:xsi="http://www.w3.org/2001/XMLSchema-instance" xsi:noNamespaceSchemaLocation="https://validation.gdn.giants-software.com/xml/schema/fillTypes.xsd">
    <fillTypes>
        <fillType name="ROADSALT" title="$l10n_fillType_roadSalt" showOnPriceTable="true" unitShort="$l10n_unit_literShort">
            <physics massPerLiter="1.2" maxPhysicalSurfaceAngle="32" />
            <economy pricePerLiter="0.1" />
            <image      hud     ="$dataS/menu/hud/fillTypes/hud_fill_roadSalt.png" />
            <textures   diffuse ="$data/fillPlanes/roadSalt_diffuse.png"
                        normal  ="$data/fillPlanes/roadSalt_normal.png"
                        specular="$data/fillPlanes/roadSalt_specular.png"
                        distance="$data/fillPlanes/distance/roadSaltDistance_diffuse.png" />
        </fillType>
    </fillTypes>
</map>